[
  {
    "content": "Создать financial_breakdown.py: Pydantic models + safe AST formula parser",
    "status": "completed"
  },
  {
    "content": "Template CRUD endpoints (admin-only)",
    "status": "completed"
  },
  {
    "content": "Generator engine + POST /api/legal/deals/{id}/final-breakdown + /financials listing",
    "status": "completed"
  },
  {
    "content": "Seed 2 default templates на startup + indexes",
    "status": "completed"
  },
  {
    "content": "Мигрировать mark_auction_won на template-based генерацию + 3 totals",
    "status": "completed"
  },
  {
    "content": "E2E тест P1.2 — 67/67 passed",
    "status": "completed"
  },
  {
    "content": "P1.3.1 regression test — 34/34 still passing",
    "status": "completed"
  },
  {
    "content": "PRD.md обновлён",
    "status": "completed"
  }
]